simiotics_s3/__init__.py
simiotics_s3/cli.py
simiotics_s3/data.py
simiotics_s3/sources.py
simiotics_s3-0.1.0.dist-info/LICENSE
simiotics_s3-0.1.0.dist-info/METADATA
simiotics_s3-0.1.0.dist-info/WHEEL
simiotics_s3-0.1.0.dist-info/entry_points.txt
simiotics_s3-0.1.0.dist-info/top_level.txt
simiotics_s3-0.1.0.dist-info/RECORD
