Metadata-Version: 2.1
Name: simiotics-s3
Version: 0.1.0
Summary: Simiotics S3 integration
Home-page: https://github.com/nkashy1/simiotics-s3
Author: Neeraj Kashyap
Author-email: neeraj@simiotics.com
License: UNKNOWN
Platform: UNKNOWN
Classifier: License :: OSI Approved :: Apache Software License
Classifier: Development Status :: 2 - Pre-Alpha
Classifier: Programming Language :: Python
Classifier: Topic :: Scientific/Engineering :: Artificial Intelligence
Classifier: Topic :: Software Development :: Libraries
Classifier: Topic :: Software Development :: Version Control
Requires-Dist: boto3
Requires-Dist: simiotics
